Workbook

Sheet Overview
A2: School ERP development progress
A3: 296 screens across 25 modules. Counts update when the team edits the tracker. | H3: Review date | I3: =TODAY()
A4: Screens in scope | B4: =COUNTA('Screen Tracker'!$A$7:$A$302) | D4: No owner | F4: =COUNTBLANK('Screen Tracker'!$F$7:$F$302) | H4: Baseline: mockups are ready. Implementation, owners and deadlines have not been assessed.
A5: Mockups ready | B5: =COUNTIFS('Screen Tracker'!$I$7:$I$302,"Ready") | D5: No deadline | F5: =COUNTIFS('Screen Tracker'!$Y$7:$Y$302,"No deadline")
A6: Development verified | B6: =COUNTIFS('Screen Tracker'!$X$7:$X$302,"Yes") | D6: Blocked | F6: =COUNTIFS('Screen Tracker'!$W$7:$W$302,"Blocked")
A7: Released | B7: =COUNTIFS('Screen Tracker'!$W$7:$W$302,"Released") | D7: Overdue | F7: =COUNTIFS('Screen Tracker'!$Y$7:$Y$302,"Overdue") | H7: Completion measures verified screens, not hours or effort. Shared services are tracked separately. This workbook is updated manually.
A8: Verified completion rate | B8: =B6/B4 | D8: Due within 7 days | F8: =COUNTIFS('Screen Tracker'!$Y$7:$Y$302,"Due soon")
A9: Not assessed | B9: =COUNTIFS('Screen Tracker'!$W$7:$W$302,"Not assessed") | D9: Release needs review | F9: =COUNTIFS('Screen Tracker'!$W$7:$W$302,"Review release")
A10: Shared tasks verified | B10: =COUNTIFS('Shared Work'!$J$7:$J$22,"Yes") | D10: Rework / rolled back | F10: =COUNTIFS('Screen Tracker'!$W$7:$W$302,"Rework")+COUNTIFS('Screen Tracker'!$W$7:$W$302,"Rolled back")
A12: Filter Screen Tracker by owner, sprint, module or state. Enter zero open critical/high bugs only after checking.
A13: Progress by module
A14: Module | B14: Screens | C14: Frontend done | D14: API resolved | E14: Integrated | F14: QA passed | G14: Dev verified | H14: Released | I14: Blocked | J14: Overdue
A15: Public Website & Authentication | B15: =COUNTIFS('Screen Tracker'!$C$7:$C$302,$A15) | C15: =COUNTIFS('Screen Tracker'!$C$7:$C$302,$A15,'Screen Tracker'!$J$7:$J$302,"Done") | D15: =COUNTIFS('Screen Tracker'!$C$7:$C$302,$A15,'Screen Tracker'!$K$7:$K$302,"Done")+COUNTIFS('Screen Tracker'!$C$7:$C$302,$A15,'Screen Tracker'!$K$7:$K$302,"Not required",'Screen Tracker'!$V$7:$V$302,"<>") | E15: =COUNTIFS('Screen Tracker'!$C$7:$C$302,$A15,'Screen Tracker'!$L$7:$L$302,"Done")+COUNTIFS('Screen Tracker'!$C$7:$C$302,$A15,'Screen Tracker'!$L$7:$L$302,"Not required",'Screen Tracker'!$V$7:$V$302,"<>") | F15: =COUNTIFS('Screen Tracker'!$C$7:$C$302,$A15,'Screen Tracker'!$M$7:$M$302,"Passed") | G15: =COUNTIFS('Screen Tracker'!$C$7:$C$302,$A15,'Screen Tracker'!$X$7:$X$302,"Yes") | H15: =COUNTIFS('Screen Tracker'!$C$7:$C$302,$A15,'Screen Tracker'!$W$7:$W$302,"Released") | I15: =COUNTIFS('Screen Tracker'!$C$7:$C$302,$A15,'Screen Tracker'!$W$7:$W$302,"Blocked") | J15: =COUNTIFS('Screen Tracker'!$C$7:$C$302,$A15,'Screen Tracker'!$Y$7:$Y$302,"Overdue")
A16: Super Admin / SaaS Administration | B16: =COUNTIFS('Screen Tracker'!$C$7:$C$302,$A16) | C16: =COUNTIFS('Screen Tracker'!$C$7:$C$302,$A16,'Screen Tracker'!$J$7:$J$302,"Done") | D16: =COUNTIFS('Screen Tracker'!$C$7:$C$302,$A16,'Screen Tracker'!$K$7:$K$302,"Done")+COUNTIFS('Screen Tracker'!$C$7:$C$302,$A16,'Screen Tracker'!$K$7:$K$302,"Not required",'Screen Tracker'!$V$7:$V$302,"<>") | E16: =COUNTIFS('Screen Tracker'!$C$7:$C$302,$A16,'Screen Tracker'!$L$7:$L$302,"Done")+COUNTIFS('Screen Tracker'!$C$7:$C$302,$A16,'Screen Tracker'!$L$7:$L$302,"Not required",'Screen Tracker'!$V$7:$V$302,"<>") | F16: =COUNTIFS('Screen Tracker'!$C$7:$C$302,$A16,'Screen Tracker'!$M$7:$M$302,"Passed") | G16: =COUNTIFS('Screen Tracker'!$C$7:$C$302,$A16,'Screen Tracker'!$X$7:$X$302,"Yes") | H16: =COUNTIFS('Screen Tracker'!$C$7:$C$302,$A16,'Screen Tracker'!$W$7:$W$302,"Released") | I16: =COUNTIFS('Screen Tracker'!$C$7:$C$302,$A16,'Screen Tracker'!$W$7:$W$302,"Blocked") | J16: =COUNTIFS('Screen Tracker'!$C$7:$C$302,$A16,'Screen Tracker'!$Y$7:$Y$302,"Overdue")
A17: Organization / School / Branch Setup | B17: =COUNTIFS('Screen Tracker'!$C$7:$C$302,$A17) | C17: =COUNTIFS('Screen Tracker'!$C$7:$C$302,$A17,'Screen Tracker'!$J$7:$J$302,"Done") | D17: =COUNTIFS('Screen Tracker'!$C$7:$C$302,$A17,'Screen Tracker'!$K$7:$K$302,"Done")+COUNTIFS('Screen Tracker'!$C$7:$C$302,$A17,'Screen Tracker'!$K$7:$K$302,"Not required",'Screen Tracker'!$V$7:$V$302,"<>") | E17: =COUNTIFS('Screen Tracker'!$C$7:$C$302,$A17,'Screen Tracker'!$L$7:$L$302,"Done")+COUNTIFS('Screen Tracker'!$C$7:$C$302,$A17,'Screen Tracker'!$L$7:$L$302,"Not required",'Screen Tracker'!$V$7:$V$302,"<>") | F17: =COUNTIFS('Screen Tracker'!$C$7:$C$302,$A17,'Screen Tracker'!$M$7:$M$302,"Passed") | G17: =COUNTIFS('Screen Tracker'!$C$7:$C$302,$A17,'Screen Tracker'!$X$7:$X$302,"Yes") | H17: =COUNTIFS('Screen Tracker'!$C$7:$C$302,$A17,'Screen Tracker'!$W$7:$W$302,"Released") | I17: =COUNTIFS('Screen Tracker'!$C$7:$C$302,$A17,'Screen Tracker'!$W$7:$W$302,"Blocked") | J17: =COUNTIFS('Screen Tracker'!$C$7:$C$302,$A17,'Screen Tracker'!$Y$7:$Y$302,"Overdue")
A18: Role Dashboards | B18: =COUNTIFS('Screen Tracker'!$C$7:$C$302,$A18) | C18: =COUNTIFS('Screen Tracker'!$C$7:$C$302,$A18,'Screen Tracker'!$J$7:$J$302,"Done") | D18: =COUNTIFS('Screen Tracker'!$C$7:$C$302,$A18,'Screen Tracker'!$K$7:$K$302,"Done")+COUNTIFS('Screen Tracker'!$C$7:$C$302,$A18,'Screen Tracker'!$K$7:$K$302,"Not required",'Screen Tracker'!$V$7:$V$302,"<>") | E18: =COUNTIFS('Screen Tracker'!$C$7:$C$302,$A18,'Screen Tracker'!$L$7:$L$302,"Done")+COUNTIFS('Screen Tracker'!$C$7:$C$302,$A18,'Screen Tracker'!$L$7:$L$302,"Not required",'Screen Tracker'!$V$7:$V$302,"<>") | F18: =COUNTIFS('Screen Tracker'!$C$7:$C$302,$A18,'Screen Tracker'!$M$7:$M$302,"Passed") | G18: =COUNTIFS('Screen Tracker'!$C$7:$C$302,$A18,'Screen Tracker'!$X$7:$X$302,"Yes") | H18: =COUNTIFS('Screen Tracker'!$C$7:$C$302,$A18,'Screen Tracker'!$W$7:$W$302,"Released") | I18: =COUNTIFS('Screen Tracker'!$C$7:$C$302,$A18,'Screen Tracker'!$W$7:$W$302,"Blocked") | J18: =COUNTIFS('Screen Tracker'!$C$7:$C$302,$A18,'Screen Tracker'!$Y$7:$Y$302,"Overdue")
A19: Admissions & Enquiries | B19: =COUNTIFS('Screen Tracker'!$C$7:$C$302,$A19) | C19: =COUNTIFS('Screen Tracker'!$C$7:$C$302,$A19,'Screen Tracker'!$J$7:$J$302,"Done") | D19: =COUNTIFS('Screen Tracker'!$C$7:$C$302,$A19,'Screen Tracker'!$K$7:$K$302,"Done")+COUNTIFS('Screen Tracker'!$C$7:$C$302,$A19,'Screen Tracker'!$K$7:$K$302,"Not required",'Screen Tracker'!$V$7:$V$302,"<>") | E19: =COUNTIFS('Screen Tracker'!$C$7:$C$302,$A19,'Screen Tracker'!$L$7:$L$302,"Done")+COUNTIFS('Screen Tracker'!$C$7:$C$302,$A19,'Screen Tracker'!$L$7:$L$302,"Not required",'Screen Tracker'!$V$7:$V$302,"<>") | F19: =COUNTIFS('Screen Tracker'!$C$7:$C$302,$A19,'Screen Tracker'!$M$7:$M$302,"Passed") | G19: =COUNTIFS('Screen Tracker'!$C$7:$C$302,$A19,'Screen Tracker'!$X$7:$X$302,"Yes") | H19: =COUNTIFS('Screen Tracker'!$C$7:$C$302,$A19,'Screen Tracker'!$W$7:$W$302,"Released") | I19: =COUNTIFS('Screen Tracker'!$C$7:$C$302,$A19,'Screen Tracker'!$W$7:$W$302,"Blocked") | J19: =COUNTIFS('Screen Tracker'!$C$7:$C$302,$A19,'Screen Tracker'!$Y$7:$Y$302,"Overdue")
A20: Students | B20: =COUNTIFS('Screen Tracker'!$C$7:$C$302,$A20) | C20: =COUNTIFS('Screen Tracker'!$C$7:$C$302,$A20,'Screen Tracker'!$J$7:$J$302,"Done") | D20: =COUNTIFS('Screen Tracker'!$C$7:$C$302,$A20,'Screen Tracker'!$K$7:$K$302,"Done")+COUNTIFS('Screen Tracker'!$C$7:$C$302,$A20,'Screen Tracker'!$K$7:$K$302,"Not required",'Screen Tracker'!$V$7:$V$302,"<>") | E20: =COUNTIFS('Screen Tracker'!$C$7:$C$302,$A20,'Screen Tracker'!$L$7:$L$302,"Done")+COUNTIFS('Screen Tracker'!$C$7:$C$302,$A20,'Screen Tracker'!$L$7:$L$302,"Not required",'Screen Tracker'!$V$7:$V$302,"<>") | F20: =COUNTIFS('Screen Tracker'!$C$7:$C$302,$A20,'Screen Tracker'!$M$7:$M$302,"Passed") | G20: =COUNTIFS('Screen Tracker'!$C$7:$C$302,$A20,'Screen Tracker'!$X$7:$X$302,"Yes") | H20: =COUNTIFS('Screen Tracker'!$C$7:$C$302,$A20,'Screen Tracker'!$W$7:$W$302,"Released") | I20: =COUNTIFS('Screen Tracker'!$C$7:$C$302,$A20,'Screen Tracker'!$W$7:$W$302,"Blocked") | J20: =COUNTIFS('Screen Tracker'!$C$7:$C$302,$A20,'Screen Tracker'!$Y$7:$Y$302,"Overdue")
A21: Parents & Guardians | B21: =COUNTIFS('Screen Tracker'!$C$7:$C$302,$A21) | C21: =COUNTIFS('Screen Tracker'!$C$7:$C$302,$A21,'Screen Tracker'!$J$7:$J$302,"Done") | D21: =COUNTIFS('Screen Tracker'!$C$7:$C$302,$A21,'Screen Tracker'!$K$7:$K$302,"Done")+COUNTIFS('Screen Tracker'!$C$7:$C$302,$A21,'Screen Tracker'!$K$7:$K$302,"Not required",'Screen Tracker'!$V$7:$V$302,"<>") | E21: =COUNTIFS('Screen Tracker'!$C$7:$C$302,$A21,'Screen Tracker'!$L$7:$L$302,"Done")+COUNTIFS('Screen Tracker'!$C$7:$C$302,$A21,'Screen Tracker'!$L$7:$L$302,"Not required",'Screen Tracker'!$V$7:$V$302,"<>") | F21: =COUNTIFS('Screen Tracker'!$C$7:$C$302,$A21,'Screen Tracker'!$M$7:$M$302,"Passed") | G21: =COUNTIFS('Screen Tracker'!$C$7:$C$302,$A21,'Screen Tracker'!$X$7:$X$302,"Yes") | H21: =COUNTIFS('Screen Tracker'!$C$7:$C$302,$A21,'Screen Tracker'!$W$7:$W$302,"Released") | I21: =COUNTIFS('Screen Tracker'!$C$7:$C$302,$A21,'Screen Tracker'!$W$7:$W$302,"Blocked") | J21: =COUNTIFS('Screen Tracker'!$C$7:$C$302,$A21,'Screen Tracker'!$Y$7:$Y$302,"Overdue")
A22: Teachers & Staff | B22: =COUNTIFS('Screen Tracker'!$C$7:$C$302,$A22) | C22: =COUNTIFS('Screen Tracker'!$C$7:$C$302,$A22,'Screen Tracker'!$J$7:$J$302,"Done") | D22: =COUNTIFS('Screen Tracker'!$C$7:$C$302,$A22,'Screen Tracker'!$K$7:$K$302,"Done")+COUNTIFS('Screen Tracker'!$C$7:$C$302,$A22,'Screen Tracker'!$K$7:$K$302,"Not required",'Screen Tracker'!$V$7:$V$302,"<>") | E22: =COUNTIFS('Screen Tracker'!$C$7:$C$302,$A22,'Screen Tracker'!$L$7:$L$302,"Done")+COUNTIFS('Screen Tracker'!$C$7:$C$302,$A22,'Screen Tracker'!$L$7:$L$302,"Not required",'Screen Tracker'!$V$7:$V$302,"<>") | F22: =COUNTIFS('Screen Tracker'!$C$7:$C$302,$A22,'Screen Tracker'!$M$7:$M$302,"Passed") | G22: =COUNTIFS('Screen Tracker'!$C$7:$C$302,$A22,'Screen Tracker'!$X$7:$X$302,"Yes") | H22: =COUNTIFS('Screen Tracker'!$C$7:$C$302,$A22,'Screen Tracker'!$W$7:$W$302,"Released") | I22: =COUNTIFS('Screen Tracker'!$C$7:$C$302,$A22,'Screen Tracker'!$W$7:$W$302,"Blocked") | J22: =COUNTIFS('Screen Tracker'!$C$7:$C$302,$A22,'Screen Tracker'!$Y$7:$Y$302,"Overdue")
A23: Academics & Curriculum | B23: =COUNTIFS('Screen Tracker'!$C$7:$C$302,$A23) | C23: =COUNTIFS('Screen Tracker'!$C$7:$C$302,$A23,'Screen Tracker'!$J$7:$J$302,"Done") | D23: =COUNTIFS('Screen Tracker'!$C$7:$C$302,$A23,'Screen Tracker'!$K$7:$K$302,"Done")+COUNTIFS('Screen Tracker'!$C$7:$C$302,$A23,'Screen Tracker'!$K$7:$K$302,"Not required",'Screen Tracker'!$V$7:$V$302,"<>") | E23: =COUNTIFS('Screen Tracker'!$C$7:$C$302,$A23,'Screen Tracker'!$L$7:$L$302,"Done")+COUNTIFS('Screen Tracker'!$C$7:$C$302,$A23,'Screen Tracker'!$L$7:$L$302,"Not required",'Screen Tracker'!$V$7:$V$302,"<>") | F23: =COUNTIFS('Screen Tracker'!$C$7:$C$302,$A23,'Screen Tracker'!$M$7:$M$302,"Passed") | G23: =COUNTIFS('Screen Tracker'!$C$7:$C$302,$A23,'Screen Tracker'!$X$7:$X$302,"Yes") | H23: =COUNTIFS('Screen Tracker'!$C$7:$C$302,$A23,'Screen Tracker'!$W$7:$W$302,"Released") | I23: =COUNTIFS('Screen Tracker'!$C$7:$C$302,$A23,'Screen Tracker'!$W$7:$W$302,"Blocked") | J23: =COUNTIFS('Screen Tracker'!$C$7:$C$302,$A23,'Screen Tracker'!$Y$7:$Y$302,"Overdue")
A24: Student Attendance | B24: =COUNTIFS('Screen Tracker'!$C$7:$C$302,$A24) | C24: =COUNTIFS('Screen Tracker'!$C$7:$C$302,$A24,'Screen Tracker'!$J$7:$J$302,"Done") | D24: =COUNTIFS('Screen Tracker'!$C$7:$C$302,$A24,'Screen Tracker'!$K$7:$K$302,"Done")+COUNTIFS('Screen Tracker'!$C$7:$C$302,$A24,'Screen Tracker'!$K$7:$K$302,"Not required",'Screen Tracker'!$V$7:$V$302,"<>") | E24: =COUNTIFS('Screen Tracker'!$C$7:$C$302,$A24,'Screen Tracker'!$L$7:$L$302,"Done")+COUNTIFS('Screen Tracker'!$C$7:$C$302,$A24,'Screen Tracker'!$L$7:$L$302,"Not required",'Screen Tracker'!$V$7:$V$302,"<>") | F24: =COUNTIFS('Screen Tracker'!$C$7:$C$302,$A24,'Screen Tracker'!$M$7:$M$302,"Passed") | G24: =COUNTIFS('Screen Tracker'!$C$7:$C$302,$A24,'Screen Tracker'!$X$7:$X$302,"Yes") | H24: =COUNTIFS('Screen Tracker'!$C$7:$C$302,$A24,'Screen Tracker'!$W$7:$W$302,"Released") | I24: =COUNTIFS('Screen Tracker'!$C$7:$C$302,$A24,'Screen Tracker'!$W$7:$W$302,"Blocked") | J24: =COUNTIFS('Screen Tracker'!$C$7:$C$302,$A24,'Screen Tracker'!$Y$7:$Y$302,"Overdue")
A25: Timetable & Substitution | B25: =COUNTIFS('Screen Tracker'!$C$7:$C$302,$A25) | C25: =COUNTIFS('Screen Tracker'!$C$7:$C$302,$A25,'Screen Tracker'!$J$7:$J$302,"Done") | D25: =COUNTIFS('Screen Tracker'!$C$7:$C$302,$A25,'Screen Tracker'!$K$7:$K$302,"Done")+COUNTIFS('Screen Tracker'!$C$7:$C$302,$A25,'Screen Tracker'!$K$7:$K$302,"Not required",'Screen Tracker'!$V$7:$V$302,"<>") | E25: =COUNTIFS('Screen Tracker'!$C$7:$C$302,$A25,'Screen Tracker'!$L$7:$L$302,"Done")+COUNTIFS('Screen Tracker'!$C$7:$C$302,$A25,'Screen Tracker'!$L$7:$L$302,"Not required",'Screen Tracker'!$V$7:$V$302,"<>") | F25: =COUNTIFS('Screen Tracker'!$C$7:$C$302,$A25,'Screen Tracker'!$M$7:$M$302,"Passed") | G25: =COUNTIFS('Screen Tracker'!$C$7:$C$302,$A25,'Screen Tracker'!$X$7:$X$302,"Yes") | H25: =COUNTIFS('Screen Tracker'!$C$7:$C$302,$A25,'Screen Tracker'!$W$7:$W$302,"Released") | I25: =COUNTIFS('Screen Tracker'!$C$7:$C$302,$A25,'Screen Tracker'!$W$7:$W$302,"Blocked") | J25: =COUNTIFS('Screen Tracker'!$C$7:$C$302,$A25,'Screen Tracker'!$Y$7:$Y$302,"Overdue")
A26: Homework & Assignments | B26: =COUNTIFS('Screen Tracker'!$C$7:$C$302,$A26) | C26: =COUNTIFS('Screen Tracker'!$C$7:$C$302,$A26,'Screen Tracker'!$J$7:$J$302,"Done") | D26: =COUNTIFS('Screen Tracker'!$C$7:$C$302,$A26,'Screen Tracker'!$K$7:$K$302,"Done")+COUNTIFS('Screen Tracker'!$C$7:$C$302,$A26,'Screen Tracker'!$K$7:$K$302,"Not required",'Screen Tracker'!$V$7:$V$302,"<>") | E26: =COUNTIFS('Screen Tracker'!$C$7:$C$302,$A26,'Screen Tracker'!$L$7:$L$302,"Done")+COUNTIFS('Screen Tracker'!$C$7:$C$302,$A26,'Screen Tracker'!$L$7:$L$302,"Not required",'Screen Tracker'!$V$7:$V$302,"<>") | F26: =COUNTIFS('Screen Tracker'!$C$7:$C$302,$A26,'Screen Tracker'!$M$7:$M$302,"Passed") | G26: =COUNTIFS('Screen Tracker'!$C$7:$C$302,$A26,'Screen Tracker'!$X$7:$X$302,"Yes") | H26: =COUNTIFS('Screen Tracker'!$C$7:$C$302,$A26,'Screen Tracker'!$W$7:$W$302,"Released") | I26: =COUNTIFS('Screen Tracker'!$C$7:$C$302,$A26,'Screen Tracker'!$W$7:$W$302,"Blocked") | J26: =COUNTIFS('Screen Tracker'!$C$7:$C$302,$A26,'Screen Tracker'!$Y$7:$Y$302,"Overdue")
... A39: Settings / Roles / Permissions / Audit | B39: =COUNTIFS('Screen Tracker'!$C$7:$C$302,$A39) | C39: =COUNTIFS('Screen Tracker'!$C$7:$C$302,$A39,'Screen Tracker'!$J$7:$J$302,"Done") | D39: =COUNTIFS('Screen Tracker'!$C$7:$C$302,$A39,'Screen Tracker'!$K$7:$K$302,"Done")+COUNTIFS('Screen Tracker'!$C$7:$C$302,$A39,'Screen Tracker'!$K$7:$K$302,"Not required",'Screen Tracker'!$V$7:$V$302,"<>") | E39: =COUNTIFS('Screen Tracker'!$C$7:$C$302,$A39,'Screen Tracker'!$L$7:$L$302,"Done")+COUNTIFS('Screen Tracker'!$C$7:$C$302,$A39,'Screen Tracker'!$L$7:$L$302,"Not required",'Screen Tracker'!$V$7:$V$302,"<>") | F39: =COUNTIFS('Screen Tracker'!$C$7:$C$302,$A39,'Screen Tracker'!$M$7:$M$302,"Passed") | G39: =COUNTIFS('Screen Tracker'!$C$7:$C$302,$A39,'Screen Tracker'!$X$7:$X$302,"Yes") | H39: =COUNTIFS('Screen Tracker'!$C$7:$C$302,$A39,'Screen Tracker'!$W$7:$W$302,"Released") | I39: =COUNTIFS('Screen Tracker'!$C$7:$C$302,$A39,'Screen Tracker'!$W$7:$W$302,"Blocked") | J39: =COUNTIFS('Screen Tracker'!$C$7:$C$302,$A39,'Screen Tracker'!$Y$7:$Y$302,"Overdue")
A40: Total | B40: =SUM(B15:B39) | C40: =SUM(C15:C39) | D40: =SUM(D15:D39) | E40: =SUM(E15:E39) | F40: =SUM(F15:F39) | G40: =SUM(G15:G39) | H40: =SUM(H15:H39) | I40: =SUM(I15:I39) | J40: =SUM(J15:J39)
A42: API resolved / Integrated includes “Not required” only when a reason is recorded. Stages are counted independently.
A44: Progress by release scope | F44: Update routine
A45: Release scope | B45: Screens | C45: Dev verified | D45: Released | F45: 1. Start with the MVP scope. Assess each screen, assign one accountable owner, sprint and due date.
A46: MVP | B46: =COUNTIFS('Screen Tracker'!$D$7:$D$302,A46) | C46: =COUNTIFS('Screen Tracker'!$D$7:$D$302,A46,'Screen Tracker'!$X$7:$X$302,"Yes") | D46: =COUNTIFS('Screen Tracker'!$D$7:$D$302,A46,'Screen Tracker'!$W$7:$W$302,"Released")
A47: Phase 2 | B47: =COUNTIFS('Screen Tracker'!$D$7:$D$302,A47) | C47: =COUNTIFS('Screen Tracker'!$D$7:$D$302,A47,'Screen Tracker'!$X$7:$X$302,"Yes") | D47: =COUNTIFS('Screen Tracker'!$D$7:$D$302,A47,'Screen Tracker'!$W$7:$W$302,"Released") | F47: 2. Update stages, blockers, next action and last updated each day. Use the SCR ID in tasks and PRs.
A48: Phase 3 | B48: =COUNTIFS('Screen Tracker'!$D$7:$D$302,A48) | C48: =COUNTIFS('Screen Tracker'!$D$7:$D$302,A48,'Screen Tracker'!$X$7:$X$302,"Yes") | D48: =COUNTIFS('Screen Tracker'!$D$7:$D$302,A48,'Screen Tracker'!$W$7:$W$302,"Released")
F49: 3. QA records test evidence and open critical/high defects. The product owner records acceptance.
A50: When development counts as verified
A51: Frontend done, API and integration done or justified as not required, QA passed, acceptance accepted, zero open critical/high bugs and no blocker. | F51: 4. Review blockers and overdue work daily. Review module delivery and the next sprint weekly.
F53: 5. Keep Shared Work current for services used by many screens. Record deployment after release.
A54: Owner, work item / PR, QA evidence and last updated must also be recorded. A production deployment counts as released only when this gate passes.

Sheet Screen Tracker
A2: Screen development tracker
A3: Amber cells are editable. Keep one row per SCR ID. Scroll right for evidence, calculated state and schedule.
A4: Source: School_ERP_296_Mock_Screens_Source.zip, 296-screen registry. Mockup baseline: School_ERP_296_Bright_Screens.zip.
A6: Screen ID | B6: Screen name | C6: Module | D6: Release scope | E6: Story IDs | F6: Owner | G6: Sprint | H6: Due date | I6: Mockup | J6: Frontend | K6: API / DB | L6: Integration | M6: QA | N6: Acceptance | O6: Open critical / high bugs | P6: Deployment | Q6: Blocker / dependency | R6: Next action | S6: Work item / PR link | T6: QA evidence link | U6: Last updated | V6: Not required reason | W6: State (calculated) | X6: Dev verified | Y6: Schedule (calculated) | Z6: Days overdue | AA6: Roles | AB6: Implemented at (audit)
A7: SCR-001 | B7: Landing / Home | C7: Public Website & Authentication | D7: MVP | E7: US-0001, US-0002 | I7: Ready | J7: Done | K7: Not required | L7: Not assessed | M7: Not assessed | N7: Not assessed | P7: Not scheduled | R7: Hero, feature cards, portal links, health badge | U7: 46285 | V7: Hero, feature cards, portal links, health badge | W7: =IF(P7="Production",IF(X7="Yes","Released","Review release"),IF(P7="Rolled back","Rolled back",IF(OR(Q7<>"",COUNTIFS(J7:N7,"Blocked")>0),"Blocked",IF(OR(M7="Failed",N7="Rejected",AND(ISNUMBER(O7),O7>0)),"Rework",IF(X7="Yes","Ready for release",IF(N7="Accepted","Verify completion",IF(OR(M7="Passed",M7="In progress",N7="In review"),"Testing / review",IF(OR(COUNTIFS(J7:L7,"In progress")>0,COUNTIFS(J7:L7,"In review")>0,COUNTIFS(J7:L7,"Done")>0),"In progress",IF(COUNTIFS(J7:N7,"Not assessed")=5,"Not assessed","Planned"))))))))) | X7: =IF(AND(J7="Done",OR(K7="Done",K7="Not required"),OR(L7="Done",L7="Not required"),M7="Passed",N7="Accepted",ISNUMBER(O7),O7=0,Q7="",F7<>"",S7<>"",T7<>"",ISNUMBER(U7),OR(AND(K7<>"Not required",L7<>"Not required"),V7<>""),P7<>"Rolled back"),"Yes","No") | Y7: =IF(X7="Yes","Completed",IF(H7="","No deadline",IF(NOT(ISNUMBER(H7)),"Check date",IF(H7<Overview!$I$3,"Overdue",IF(H7<=Overview!$I$3+7,"Due soon","On track"))))) | Z7: =IF(AND(X7<>"Yes",ISNUMBER(H7)),MAX(0,Overview!$I$3-H7),0) | AA7: All Users | AB7: /
A8: SCR-002 | B8: Workspace / Role Selection | C8: Public Website & Authentication | D8: MVP | E8: US-0003, US-0004 | I8: Ready | J8: Done | K8: Not required | L8: Not assessed | M8: Not assessed | N8: Not assessed | P8: Not scheduled | R8: Every portal, with a line on picking the right one | U8: 46285 | V8: Every portal, with a line on picking the right one | W8: =IF(P8="Production",IF(X8="Yes","Released","Review release"),IF(P8="Rolled back","Rolled back",IF(OR(Q8<>"",COUNTIFS(J8:N8,"Blocked")>0),"Blocked",IF(OR(M8="Failed",N8="Rejected",AND(ISNUMBER(O8),O8>0)),"Rework",IF(X8="Yes","Ready for release",IF(N8="Accepted","Verify completion",IF(OR(M8="Passed",M8="In progress",N8="In review"),"Testing / review",IF(OR(COUNTIFS(J8:L8,"In progress")>0,COUNTIFS(J8:L8,"In review")>0,COUNTIFS(J8:L8,"Done")>0),"In progress",IF(COUNTIFS(J8:N8,"Not assessed")=5,"Not assessed","Planned"))))))))) | X8: =IF(AND(J8="Done",OR(K8="Done",K8="Not required"),OR(L8="Done",L8="Not required"),M8="Passed",N8="Accepted",ISNUMBER(O8),O8=0,Q8="",F8<>"",S8<>"",T8<>"",ISNUMBER(U8),OR(AND(K8<>"Not required",L8<>"Not required"),V8<>""),P8<>"Rolled back"),"Yes","No") | Y8: =IF(X8="Yes","Completed",IF(H8="","No deadline",IF(NOT(ISNUMBER(H8)),"Check date",IF(H8<Overview!$I$3,"Overdue",IF(H8<=Overview!$I$3+7,"Due soon","On track"))))) | Z8: =IF(AND(X8<>"Yes",ISNUMBER(H8)),MAX(0,Overview!$I$3-H8),0) | AA8: All Users | AB8: /workspace
A9: SCR-003 | B9: Sign In | C9: Public Website & Authentication | D9: MVP | E9: US-0005, US-0006 | I9: Ready | J9: Done | K9: Done | L9: Not assessed | M9: Not assessed | N9: Not assessed | P9: Not scheduled | R9: Seven sign-in pages, each posts auth/login | U9: 46285 | W9: =IF(P9="Production",IF(X9="Yes","Released","Review release"),IF(P9="Rolled back","Rolled back",IF(OR(Q9<>"",COUNTIFS(J9:N9,"Blocked")>0),"Blocked",IF(OR(M9="Failed",N9="Rejected",AND(ISNUMBER(O9),O9>0)),"Rework",IF(X9="Yes","Ready for release",IF(N9="Accepted","Verify completion",IF(OR(M9="Passed",M9="In progress",N9="In review"),"Testing / review",IF(OR(COUNTIFS(J9:L9,"In progress")>0,COUNTIFS(J9:L9,"In review")>0,COUNTIFS(J9:L9,"Done")>0),"In progress",IF(COUNTIFS(J9:N9,"Not assessed")=5,"Not assessed","Planned"))))))))) | X9: =IF(AND(J9="Done",OR(K9="Done",K9="Not required"),OR(L9="Done",L9="Not required"),M9="Passed",N9="Accepted",ISNUMBER(O9),O9=0,Q9="",F9<>"",S9<>"",T9<>"",ISNUMBER(U9),OR(AND(K9<>"Not required",L9<>"Not required"),V9<>""),P9<>"Rolled back"),"Yes","No") | Y9: =IF(X9="Yes","Completed",IF(H9="","No deadline",IF(NOT(ISNUMBER(H9)),"Check date",IF(H9<Overview!$I$3,"Overdue",IF(H9<=Overview!$I$3+7,"Due soon","On track"))))) | Z9: =IF(AND(X9<>"Yes",ISNUMBER(H9)),MAX(0,Overview!$I$3-H9),0) | AA9: All Users | AB9: /school/login and six other portals
A10: SCR-004 | B10: Forgot Password | C10: Public Website & Authentication | D10: MVP | E10: US-0007, US-0008 | I10: Ready | J10: Done | K10: Done | L10: Not assessed | M10: Not assessed | N10: Not assessed | P10: Not scheduled | R10: Same answer whether the account exists or not | U10: 46285 | W10: =IF(P10="Production",IF(X10="Yes","Released","Review release"),IF(P10="Rolled back","Rolled back",IF(OR(Q10<>"",COUNTIFS(J10:N10,"Blocked")>0),"Blocked",IF(OR(M10="Failed",N10="Rejected",AND(ISNUMBER(O10),O10>0)),"Rework",IF(X10="Yes","Ready for release",IF(N10="Accepted","Verify completion",IF(OR(M10="Passed",M10="In progress",N10="In review"),"Testing / review",IF(OR(COUNTIFS(J10:L10,"In progress")>0,COUNTIFS(J10:L10,"In review")>0,COUNTIFS(J10:L10,"Done")>0),"In progress",IF(COUNTIFS(J10:N10,"Not assessed")=5,"Not assessed","Planned"))))))))) | X10: =IF(AND(J10="Done",OR(K10="Done",K10="Not required"),OR(L10="Done",L10="Not required"),M10="Passed",N10="Accepted",ISNUMBER(O10),O10=0,Q10="",F10<>"",S10<>"",T10<>"",ISNUMBER(U10),OR(AND(K10<>"Not required",L10<>"Not required"),V10<>""),P10<>"Rolled back"),"Yes","No") | Y10: =IF(X10="Yes","Completed",IF(H10="","No deadline",IF(NOT(ISNUMBER(H10)),"Check date",IF(H10<Overview!$I$3,"Overdue",IF(H10<=Overview!$I$3+7,"Due soon","On track"))))) | Z10: =IF(AND(X10<>"Yes",ISNUMBER(H10)),MAX(0,Overview!$I$3-H10),0) | AA10: All Users | AB10: /account/forgot-password
A11: SCR-005 | B11: Reset Password | C11: Public Website & Authentication | D11: MVP | E11: US-0009, US-0010 | I11: Ready | J11: Done | K11: Done | L11: Not assessed | M11: Not assessed | N11: Not assessed | P11: Not scheduled | R11: Code dies on use, on reissue and after five guesses | U11: 46285 | W11: =IF(P11="Production",IF(X11="Yes","Released","Review release"),IF(P11="Rolled back","Rolled back",IF(OR(Q11<>"",COUNTIFS(J11:N11,"Blocked")>0),"Blocked",IF(OR(M11="Failed",N11="Rejected",AND(ISNUMBER(O11),O11>0)),"Rework",IF(X11="Yes","Ready for release",IF(N11="Accepted","Verify completion",IF(OR(M11="Passed",M11="In progress",N11="In review"),"Testing / review",IF(OR(COUNTIFS(J11:L11,"In progress")>0,COUNTIFS(J11:L11,"In review")>0,COUNTIFS(J11:L11,"Done")>0),"In progress",IF(COUNTIFS(J11:N11,"Not assessed")=5,"Not assessed","Planned"))))))))) | X11: =IF(AND(J11="Done",OR(K11="Done",K11="Not required"),OR(L11="Done",L11="Not required"),M11="Passed",N11="Accepted",ISNUMBER(O11),O11=0,Q11="",F11<>"",S11<>"",T11<>"",ISNUMBER(U11),OR(AND(K11<>"Not required",L11<>"Not required"),V11<>""),P11<>"Rolled back"),"Yes","No") | Y11: =IF(X11="Yes","Completed",IF(H11="","No deadline",IF(NOT(ISNUMBER(H11)),"Check date",IF(H11<Overview!$I$3,"Overdue",IF(H11<=Overview!$I$3+7,"Due soon","On track"))))) | Z11: =IF(AND(X11<>"Yes",ISNUMBER(H11)),MAX(0,Overview!$I$3-H11),0) | AA11: All Users | AB11: /account/reset-password
A12: SCR-006 | B12: OTP / Two-Factor Verification | C12: Public Website & Authentication | D12: Phase 2 | E12: US-0011, US-0012 | I12: Ready | J12: Not started | K12: Not started | L12: Not assessed | M12: Not assessed | N12: Not assessed | P12: Not scheduled | R12: Parent login says OTP coming soon | U12: 46285 | W12: =IF(P12="Production",IF(X12="Yes","Released","Review release"),IF(P12="Rolled back","Rolled back",IF(OR(Q12<>"",COUNTIFS(J12:N12,"Blocked")>0),"Blocked",IF(OR(M12="Failed",N12="Rejected",AND(ISNUMBER(O12),O12>0)),"Rework",IF(X12="Yes","Ready for release",IF(N12="Accepted","Verify completion",IF(OR(M12="Passed",M12="In progress",N12="In review"),"Testing / review",IF(OR(COUNTIFS(J12:L12,"In progress")>0,COUNTIFS(J12:L12,"In review")>0,COUNTIFS(J12:L12,"Done")>0),"In progress",IF(COUNTIFS(J12:N12,"Not assessed")=5,"Not assessed","Planned"))))))))) | X12: =IF(AND(J12="Done",OR(K12="Done",K12="Not required"),OR(L12="Done",L12="Not required"),M12="Passed",N12="Accepted",ISNUMBER(O12),O12=0,Q12="",F12<>"",S12<>"",T12<>"",ISNUMBER(U12),OR(AND(K12<>"Not required",L12<>"Not required"),V12<>""),P12<>"Rolled back"),"Yes","No") | Y12: =IF(X12="Yes","Completed",IF(H12="","No deadline",IF(NOT(ISNUMBER(H12)),"Check date",IF(H12<Overview!$I$3,"Overdue",IF(H12<=Overview!$I$3+7,"Due soon","On track"))))) | Z12: =IF(AND(X12<>"Yes",ISNUMBER(H12)),MAX(0,Overview!$I$3-H12),0) | AA12: All Users | AB12: -
A13: SCR-007 | B13: First Login / Change Password | C13: Public Website & Authentication | D13: Phase 2 | E13: US-0013, US-0014 | I13: Ready | J13: Done | K13: Done | L13: Not assessed | M13: Not assessed | N13: Not assessed | P13: Not scheduled | R13: Every guard forces it when somebody else set the password | U13: 46285 | W13: =IF(P13="Production",IF(X13="Yes","Released","Review release"),IF(P13="Rolled back","Rolled back",IF(OR(Q13<>"",COUNTIFS(J13:N13,"Blocked")>0),"Blocked",IF(OR(M13="Failed",N13="Rejected",AND(ISNUMBER(O13),O13>0)),"Rework",IF(X13="Yes","Ready for release",IF(N13="Accepted","Verify completion",IF(OR(M13="Passed",M13="In progress",N13="In review"),"Testing / review",IF(OR(COUNTIFS(J13:L13,"In progress")>0,COUNTIFS(J13:L13,"In review")>0,COUNTIFS(J13:L13,"Done")>0),"In progress",IF(COUNTIFS(J13:N13,"Not assessed")=5,"Not assessed","Planned"))))))))) | X13: =IF(AND(J13="Done",OR(K13="Done",K13="Not required"),OR(L13="Done",L13="Not required"),M13="Passed",N13="Accepted",ISNUMBER(O13),O13=0,Q13="",F13<>"",S13<>"",T13<>"",ISNUMBER(U13),OR(AND(K13<>"Not required",L13<>"Not required"),V13<>""),P13<>"Rolled back"),"Yes","No") | Y13: =IF(X13="Yes","Completed",IF(H13="","No deadline",IF(NOT(ISNUMBER(H13)),"Check date",IF(H13<Overview!$I$3,"Overdue",IF(H13<=Overview!$I$3+7,"Due soon","On track"))))) | Z13: =IF(AND(X13<>"Yes",ISNUMBER(H13)),MAX(0,Overview!$I$3-H13),0) | AA13: All Users | AB13: /account/change-password
A14: SCR-008 | B14: Access Denied / Session Expired | C14: Public Website & Authentication | D14: Phase 2 | E14: US-0015, US-0016 | I14: Ready | J14: Done | K14: Not required | L14: Not assessed | M14: Not assessed | N14: Not assessed | P14: Not scheduled | R14: Expired and forbidden, and the 401 interceptor routes here | U14: 46285 | V14: Expired and forbidden, and the 401 interceptor routes here | W14: =IF(P14="Production",IF(X14="Yes","Released","Review release"),IF(P14="Rolled back","Rolled back",IF(OR(Q14<>"",COUNTIFS(J14:N14,"Blocked")>0),"Blocked",IF(OR(M14="Failed",N14="Rejected",AND(ISNUMBER(O14),O14>0)),"Rework",IF(X14="Yes","Ready for release",IF(N14="Accepted","Verify completion",IF(OR(M14="Passed",M14="In progress",N14="In review"),"Testing / review",IF(OR(COUNTIFS(J14:L14,"In progress")>0,COUNTIFS(J14:L14,"In review")>0,COUNTIFS(J14:L14,"Done")>0),"In progress",IF(COUNTIFS(J14:N14,"Not assessed")=5,"Not assessed","Planned"))))))))) | X14: =IF(AND(J14="Done",OR(K14="Done",K14="Not required"),OR(L14="Done",L14="Not required"),M14="Passed",N14="Accepted",ISNUMBER(O14),O14=0,Q14="",F14<>"",S14<>"",T14<>"",ISNUMBER(U14),OR(AND(K14<>"Not required",L14<>"Not required"),V14<>""),P14<>"Rolled back"),"Yes","No") | Y14: =IF(X14="Yes","Completed",IF(H14="","No deadline",IF(NOT(ISNUMBER(H14)),"Check date",IF(H14<Overview!$I$3,"Overdue",IF(H14<=Overview!$I$3+7,"Due soon","On track"))))) | Z14: =IF(AND(X14<>"Yes",ISNUMBER(H14)),MAX(0,Overview!$I$3-H14),0) | AA14: All Users | AB14: /account/denied
A15: SCR-009 | B15: Platform Dashboard | C15: Super Admin / SaaS Administration | D15: MVP | E15: US-0017, US-0018 | I15: Ready | J15: Done | K15: Done | L15: Not assessed | M15: Not assessed | N15: Not assessed | P15: Not scheduled | R15: Usage counters, renewals, CSV export | U15: 46285 | W15: =IF(P15="Production",IF(X15="Yes","Released","Review release"),IF(P15="Rolled back","Rolled back",IF(OR(Q15<>"",COUNTIFS(J15:N15,"Blocked")>0),"Blocked",IF(OR(M15="Failed",N15="Rejected",AND(ISNUMBER(O15),O15>0)),"Rework",IF(X15="Yes","Ready for release",IF(N15="Accepted","Verify completion",IF(OR(M15="Passed",M15="In progress",N15="In review"),"Testing / review",IF(OR(COUNTIFS(J15:L15,"In progress")>0,COUNTIFS(J15:L15,"In review")>0,COUNTIFS(J15:L15,"Done")>0),"In progress",IF(COUNTIFS(J15:N15,"Not assessed")=5,"Not assessed","Planned"))))))))) | X15: =IF(AND(J15="Done",OR(K15="Done",K15="Not required"),OR(L15="Done",L15="Not required"),M15="Passed",N15="Accepted",ISNUMBER(O15),O15=0,Q15="",F15<>"",S15<>"",T15<>"",ISNUMBER(U15),OR(AND(K15<>"Not required",L15<>"Not required"),V15<>""),P15<>"Rolled back"),"Yes","No") | Y15: =IF(X15="Yes","Completed",IF(H15="","No deadline",IF(NOT(ISNUMBER(H15)),"Check date",IF(H15<Overview!$I$3,"Overdue",IF(H15<=Overview!$I$3+7,"Due soon","On track"))))) | Z15: =IF(AND(X15<>"Yes",ISNUMBER(H15)),MAX(0,Overview!$I$3-H15),0) | AA15: Super Admin | AB15: /super-admin
A16: SCR-010 | B16: Organizations List | C16: Super Admin / SaaS Administration | D16: MVP | E16: US-0019, US-0020 | I16: Ready | J16: Done | K16: Done | L16: Not assessed | M16: Not assessed | N16: Not assessed | P16: Not scheduled | R16: Paginated table with search and status | U16: 46285 | W16: =IF(P16="Production",IF(X16="Yes","Released","Review release"),IF(P16="Rolled back","Rolled back",IF(OR(Q16<>"",COUNTIFS(J16:N16,"Blocked")>0),"Blocked",IF(OR(M16="Failed",N16="Rejected",AND(ISNUMBER(O16),O16>0)),"Rework",IF(X16="Yes","Ready for release",IF(N16="Accepted","Verify completion",IF(OR(M16="Passed",M16="In progress",N16="In review"),"Testing / review",IF(OR(COUNTIFS(J16:L16,"In progress")>0,COUNTIFS(J16:L16,"In review")>0,COUNTIFS(J16:L16,"Done")>0),"In progress",IF(COUNTIFS(J16:N16,"Not assessed")=5,"Not assessed","Planned"))))))))) | X16: =IF(AND(J16="Done",OR(K16="Done",K16="Not required"),OR(L16="Done",L16="Not required"),M16="Passed",N16="Accepted",ISNUMBER(O16),O16=0,Q16="",F16<>"",S16<>"",T16<>"",ISNUMBER(U16),OR(AND(K16<>"Not required",L16<>"Not required"),V16<>""),P16<>"Rolled back"),"Yes","No") | Y16: =IF(X16="Yes","Completed",IF(H16="","No deadline",IF(NOT(ISNUMBER(H16)),"Check date",IF(H16<Overview!$I$3,"Overdue",IF(H16<=Overview!$I$3+7,"Due soon","On track"))))) | Z16: =IF(AND(X16<>"Yes",ISNUMBER(H16)),MAX(0,Overview!$I$3-H16),0) | AA16: Super Admin | AB16: /super-admin/tenants
A17: SCR-011 | B17: Add Organization | C17: Super Admin / SaaS Administration | D17: MVP | E17: US-0021, US-0022 | I17: Ready | J17: Done | K17: Done | L17: Not assessed | M17: Not assessed | N17: Not assessed | P17: Not scheduled | R17: Creates tenant, school and admin | U17: 46285 | W17: =IF(P17="Production",IF(X17="Yes","Released","Review release"),IF(P17="Rolled back","Rolled back",IF(OR(Q17<>"",COUNTIFS(J17:N17,"Blocked")>0),"Blocked",IF(OR(M17="Failed",N17="Rejected",AND(ISNUMBER(O17),O17>0)),"Rework",IF(X17="Yes","Ready for release",IF(N17="Accepted","Verify completion",IF(OR(M17="Passed",M17="In progress",N17="In review"),"Testing / review",IF(OR(COUNTIFS(J17:L17,"In progress")>0,COUNTIFS(J17:L17,"In review")>0,COUNTIFS(J17:L17,"Done")>0),"In progress",IF(COUNTIFS(J17:N17,"Not assessed")=5,"Not assessed","Planned"))))))))) | X17: =IF(AND(J17="Done",OR(K17="Done",K17="Not required"),OR(L17="Done",L17="Not required"),M17="Passed",N17="Accepted",ISNUMBER(O17),O17=0,Q17="",F17<>"",S17<>"",T17<>"",ISNUMBER(U17),OR(AND(K17<>"Not required",L17<>"Not required"),V17<>""),P17<>"Rolled back"),"Yes","No") | Y17: =IF(X17="Yes","Completed",IF(H17="","No deadline",IF(NOT(ISNUMBER(H17)),"Check date",IF(H17<Overview!$I$3,"Overdue",IF(H17<=Overview!$I$3+7,"Due soon","On track"))))) | Z17: =IF(AND(X17<>"Yes",ISNUMBER(H17)),MAX(0,Overview!$I$3-H17),0) | AA17: Super Admin | AB17: /super-admin/tenants
A18: SCR-012 | B18: Organization Details | C18: Super Admin / SaaS Administration | D18: Phase 2 | E18: US-0023, US-0024 | I18: Ready | J18: Done | K18: Done | L18: Not assessed | M18: Not assessed | N18: Not assessed | P18: Not scheduled | R18: Subscription, schools, usage, payments, suspend | U18: 46285 | W18: =IF(P18="Production",IF(X18="Yes","Released","Review release"),IF(P18="Rolled back","Rolled back",IF(OR(Q18<>"",COUNTIFS(J18:N18,"Blocked")>0),"Blocked",IF(OR(M18="Failed",N18="Rejected",AND(ISNUMBER(O18),O18>0)),"Rework",IF(X18="Yes","Ready for release",IF(N18="Accepted","Verify completion",IF(OR(M18="Passed",M18="In progress",N18="In review"),"Testing / review",IF(OR(COUNTIFS(J18:L18,"In progress")>0,COUNTIFS(J18:L18,"In review")>0,COUNTIFS(J18:L18,"Done")>0),"In progress",IF(COUNTIFS(J18:N18,"Not assessed")=5,"Not assessed","Planned"))))))))) | X18: =IF(AND(J18="Done",OR(K18="Done",K18="Not required"),OR(L18="Done",L18="Not required"),M18="Passed",N18="Accepted",ISNUMBER(O18),O18=0,Q18="",F18<>"",S18<>"",T18<>"",ISNUMBER(U18),OR(AND(K18<>"Not required",L18<>"Not required"),V18<>""),P18<>"Rolled back"),"Yes","No") | Y18: =IF(X18="Yes","Completed",IF(H18="","No deadline",IF(NOT(ISNUMBER(H18)),"Check date",IF(H18<Overview!$I$3,"Overdue",IF(H18<=Overview!$I$3+7,"Due soon","On track"))))) | Z18: =IF(AND(X18<>"Yes",ISNUMBER(H18)),MAX(0,Overview!$I$3-H18),0) | AA18: Super Admin | AB18: /super-admin/tenants/[id]
A19: SCR-013 | B19: Subscription Plans | C19: Super Admin / SaaS Administration | D19: Phase 2 | E19: US-0025, US-0026 | I19: Ready | J19: Done | K19: Done | L19: Not assessed | M19: Not assessed | N19: Not assessed | P19: Not scheduled | R19: List plus create and edit | U19: 46285 | W19: =IF(P19="Production",IF(X19="Yes","Released","Review release"),IF(P19="Rolled back","Rolled back",IF(OR(Q19<>"",COUNTIFS(J19:N19,"Blocked")>0),"Blocked",IF(OR(M19="Failed",N19="Rejected",AND(ISNUMBER(O19),O19>0)),"Rework",IF(X19="Yes","Ready for release",IF(N19="Accepted","Verify completion",IF(OR(M19="Passed",M19="In progress",N19="In review"),"Testing / review",IF(OR(COUNTIFS(J19:L19,"In progress")>0,COUNTIFS(J19:L19,"In review")>0,COUNTIFS(J19:L19,"Done")>0),"In progress",IF(COUNTIFS(J19:N19,"Not assessed")=5,"Not assessed","Planned"))))))))) | X19: =IF(AND(J19="Done",OR(K19="Done",K19="Not required"),OR(L19="Done",L19="Not required"),M19="Passed",N19="Accepted",ISNUMBER(O19),O19=0,Q19="",F19<>"",S19<>"",T19<>"",ISNUMBER(U19),OR(AND(K19<>"Not required",L19<>"Not required"),V19<>""),P19<>"Rolled back"),"Yes","No") | Y19: =IF(X19="Yes","Completed",IF(H19="","No deadline",IF(NOT(ISNUMBER(H19)),"Check date",IF(H19<Overview!$I$3,"Overdue",IF(H19<=Overview!$I$3+7,"Due soon","On track"))))) | Z19: =IF(AND(X19<>"Yes",ISNUMBER(H19)),MAX(0,Overview!$I$3-H19),0) | AA19: Super Admin | AB19: /super-admin/plans
A20: SCR-014 | B20: Subscriptions & Billing | C20: Super Admin / SaaS Administration | D20: Phase 2 | E20: US-0027, US-0028 | I20: Ready | J20: In progress | K20: In progress | L20: Not assessed | M20: Not assessed | N20: Not assessed | P20: Not scheduled | R20: Per-tenant cards, no billing screen | U20: 46285 | W20: =IF(P20="Production",IF(X20="Yes","Released","Review release"),IF(P20="Rolled back","Rolled back",IF(OR(Q20<>"",COUNTIFS(J20:N20,"Blocked")>0),"Blocked",IF(OR(M20="Failed",N20="Rejected",AND(ISNUMBER(O20),O20>0)),"Rework",IF(X20="Yes","Ready for release",IF(N20="Accepted","Verify completion",IF(OR(M20="Passed",M20="In progress",N20="In review"),"Testing / review",IF(OR(COUNTIFS(J20:L20,"In progress")>0,COUNTIFS(J20:L20,"In review")>0,COUNTIFS(J20:L20,"Done")>0),"In progress",IF(COUNTIFS(J20:N20,"Not assessed")=5,"Not assessed","Planned"))))))))) | X20: =IF(AND(J20="Done",OR(K20="Done",K20="Not required"),OR(L20="Done",L20="Not required"),M20="Passed",N20="Accepted",ISNUMBER(O20),O20=0,Q20="",F20<>"",S20<>"",T20<>"",ISNUMBER(U20),OR(AND(K20<>"Not required",L20<>"Not required"),V20<>""),P20<>"Rolled back"),"Yes","No") | Y20: =IF(X20="Yes","Completed",IF(H20="","No deadline",IF(NOT(ISNUMBER(H20)),"Check date",IF(H20<Overview!$I$3,"Overdue",IF(H20<=Overview!$I$3+7,"Due soon","On track"))))) | Z20: =IF(AND(X20<>"Yes",ISNUMBER(H20)),MAX(0,Overview!$I$3-H20),0) | AA20: Super Admin | AB20: /super-admin/tenants/[id]
A21: SCR-015 | B21: Tenant Usage & Limits | C21: Super Admin / SaaS Administration | D21: Phase 2 | E21: US-0029, US-0030 | I21: Ready | J21: In progress | K21: Done | L21: Not assessed | M21: Not assessed | N21: Not assessed | P21: Not scheduled | R21: Usage versus quota card only | U21: 46285 | W21: =IF(P21="Production",IF(X21="Yes","Released","Review release"),IF(P21="Rolled back","Rolled back",IF(OR(Q21<>"",COUNTIFS(J21:N21,"Blocked")>0),"Blocked",IF(OR(M21="Failed",N21="Rejected",AND(ISNUMBER(O21),O21>0)),"Rework",IF(X21="Yes","Ready for release",IF(N21="Accepted","Verify completion",IF(OR(M21="Passed",M21="In progress",N21="In review"),"Testing / review",IF(OR(COUNTIFS(J21:L21,"In progress")>0,COUNTIFS(J21:L21,"In review")>0,COUNTIFS(J21:L21,"Done")>0),"In progress",IF(COUNTIFS(J21:N21,"Not assessed")=5,"Not assessed","Planned"))))))))) | X21: =IF(AND(J21="Done",OR(K21="Done",K21="Not required"),OR(L21="Done",L21="Not required"),M21="Passed",N21="Accepted",ISNUMBER(O21),O21=0,Q21="",F21<>"",S21<>"",T21<>"",ISNUMBER(U21),OR(AND(K21<>"Not required",L21<>"Not required"),V21<>""),P21<>"Rolled back"),"Yes","No") | Y21: =IF(X21="Yes","Completed",IF(H21="","No deadline",IF(NOT(ISNUMBER(H21)),"Check date",IF(H21<Overview!$I$3,"Overdue",IF(H21<=Overview!$I$3+7,"Due soon","On track"))))) | Z21: =IF(AND(X21<>"Yes",ISNUMBER(H21)),MAX(0,Overview!$I$3-H21),0) | AA21: Super Admin | AB21: /super-admin/tenants/[id]
A22: SCR-016 | B22: Platform Users | C22: Super Admin / SaaS Administration | D22: Phase 3 | E22: US-0031, US-0032 | I22: Ready | J22: Not started | K22: Not started | L22: Not assessed | M22: Not assessed | N22: Not assessed | P22: Not scheduled | R22: No platform user management | U22: 46285 | W22: =IF(P22="Production",IF(X22="Yes","Released","Review release"),IF(P22="Rolled back","Rolled back",IF(OR(Q22<>"",COUNTIFS(J22:N22,"Blocked")>0),"Blocked",IF(OR(M22="Failed",N22="Rejected",AND(ISNUMBER(O22),O22>0)),"Rework",IF(X22="Yes","Ready for release",IF(N22="Accepted","Verify completion",IF(OR(M22="Passed",M22="In progress",N22="In review"),"Testing / review",IF(OR(COUNTIFS(J22:L22,"In progress")>0,COUNTIFS(J22:L22,"In review")>0,COUNTIFS(J22:L22,"Done")>0),"In progress",IF(COUNTIFS(J22:N22,"Not assessed")=5,"Not assessed","Planned"))))))))) | X22: =IF(AND(J22="Done",OR(K22="Done",K22="Not required"),OR(L22="Done",L22="Not required"),M22="Passed",N22="Accepted",ISNUMBER(O22),O22=0,Q22="",F22<>"",S22<>"",T22<>"",ISNUMBER(U22),OR(AND(K22<>"Not required",L22<>"Not required"),V22<>""),P22<>"Rolled back"),"Yes","No") | Y22: =IF(X22="Yes","Completed",IF(H22="","No deadline",IF(NOT(ISNUMBER(H22)),"Check date",IF(H22<Overview!$I$3,"Overdue",IF(H22<=Overview!$I$3+7,"Due soon","On track"))))) | Z22: =IF(AND(X22<>"Yes",ISNUMBER(H22)),MAX(0,Overview!$I$3-H22),0) | AA22: Super Admin | AB22: -
A23: SCR-017 | B23: Support Tickets | C23: Super Admin / SaaS Administration | D23: Phase 3 | E23: US-0033, US-0034 | I23: Ready | J23: Not started | K23: Not started | L23: Not assessed | M23: Not assessed | N23: Not assessed | P23: Not scheduled | R23: No ticketing anywhere | U23: 46285 | W23: =IF(P23="Production",IF(X23="Yes","Released","Review release"),IF(P23="Rolled back","Rolled back",IF(OR(Q23<>"",COUNTIFS(J23:N23,"Blocked")>0),"Blocked",IF(OR(M23="Failed",N23="Rejected",AND(ISNUMBER(O23),O23>0)),"Rework",IF(X23="Yes","Ready for release",IF(N23="Accepted","Verify completion",IF(OR(M23="Passed",M23="In progress",N23="In review"),"Testing / review",IF(OR(COUNTIFS(J23:L23,"In progress")>0,COUNTIFS(J23:L23,"In review")>0,COUNTIFS(J23:L23,"Done")>0),"In progress",IF(COUNTIFS(J23:N23,"Not assessed")=5,"Not assessed","Planned"))))))))) | X23: =IF(AND(J23="Done",OR(K23="Done",K23="Not required"),OR(L23="Done",L23="Not required"),M23="Passed",N23="Accepted",ISNUMBER(O23),O23=0,Q23="",F23<>"",S23<>"",T23<>"",ISNUMBER(U23),OR(AND(K23<>"Not required",L23<>"Not required"),V23<>""),P23<>"Rolled back"),"Yes","No") | Y23: =IF(X23="Yes","Completed",IF(H23="","No deadline",IF(NOT(ISNUMBER(H23)),"Check date",IF(H23<Overview!$I$3,"Overdue",IF(H23<=Overview!$I$3+7,"Due soon","On track"))))) | Z23: =IF(AND(X23<>"Yes",ISNUMBER(H23)),MAX(0,Overview!$I$3-H23),0) | AA23: Super Admin | AB23: -
A24: SCR-018 | B24: System Health & Service Status | C24: Super Admin / SaaS Administration | D24: Phase 3 | E24: US-0035, US-0036 | I24: Ready | J24: In progress | K24: In progress | L24: Not assessed | M24: Not assessed | N24: Not assessed | P24: Not scheduled | R24: Online pill only, two health endpoints | U24: 46285 | W24: =IF(P24="Production",IF(X24="Yes","Released","Review release"),IF(P24="Rolled back","Rolled back",IF(OR(Q24<>"",COUNTIFS(J24:N24,"Blocked")>0),"Blocked",IF(OR(M24="Failed",N24="Rejected",AND(ISNUMBER(O24),O24>0)),"Rework",IF(X24="Yes","Ready for release",IF(N24="Accepted","Verify completion",IF(OR(M24="Passed",M24="In progress",N24="In review"),"Testing / review",IF(OR(COUNTIFS(J24:L24,"In progress")>0,COUNTIFS(J24:L24,"In review")>0,COUNTIFS(J24:L24,"Done")>0),"In progress",IF(COUNTIFS(J24:N24,"Not assessed")=5,"Not assessed","Planned"))))))))) | X24: =IF(AND(J24="Done",OR(K24="Done",K24="Not required"),OR(L24="Done",L24="Not required"),M24="Passed",N24="Accepted",ISNUMBER(O24),O24=0,Q24="",F24<>"",S24<>"",T24<>"",ISNUMBER(U24),OR(AND(K24<>"Not required",L24<>"Not required"),V24<>""),P24<>"Rolled back"),"Yes","No") | Y24: =IF(X24="Yes","Completed",IF(H24="","No deadline",IF(NOT(ISNUMBER(H24)),"Check date",IF(H24<Overview!$I$3,"Overdue",IF(H24<=Overview!$I$3+7,"Due soon","On track"))))) | Z24: =IF(AND(X24<>"Yes",ISNUMBER(H24)),MAX(0,Overview!$I$3-H24),0) | AA24: Super Admin | AB24: /
A25: SCR-019 | B25: Global Announcements | C25: Super Admin / SaaS Administration | D25: Phase 3 | E25: US-0037, US-0038 | I25: Ready | J25: Not started | K25: Not started | L25: Not assessed | M25: Not assessed | N25: Not assessed | P25: Not scheduled | R25: No global announcements | U25: 46285 | W25: =IF(P25="Production",IF(X25="Yes","Released","Review release"),IF(P25="Rolled back","Rolled back",IF(OR(Q25<>"",COUNTIFS(J25:N25,"Blocked")>0),"Blocked",IF(OR(M25="Failed",N25="Rejected",AND(ISNUMBER(O25),O25>0)),"Rework",IF(X25="Yes","Ready for release",IF(N25="Accepted","Verify completion",IF(OR(M25="Passed",M25="In progress",N25="In review"),"Testing / review",IF(OR(COUNTIFS(J25:L25,"In progress")>0,COUNTIFS(J25:L25,"In review")>0,COUNTIFS(J25:L25,"Done")>0),"In progress",IF(COUNTIFS(J25:N25,"Not assessed")=5,"Not assessed","Planned"))))))))) | X25: =IF(AND(J25="Done",OR(K25="Done",K25="Not required"),OR(L25="Done",L25="Not required"),M25="Passed",N25="Accepted",ISNUMBER(O25),O25=0,Q25="",F25<>"",S25<>"",T25<>"",ISNUMBER(U25),OR(AND(K25<>"Not required",L25<>"Not required"),V25<>""),P25<>"Rolled back"),"Yes","No") | Y25: =IF(X25="Yes","Completed",IF(H25="","No deadline",IF(NOT(ISNUMBER(H25)),"Check date",IF(H25<Overview!$I$3,"Overdue",IF(H25<=Overview!$I$3+7,"Due soon","On track"))))) | Z25: =IF(AND(X25<>"Yes",ISNUMBER(H25)),MAX(0,Overview!$I$3-H25),0) | AA25: Super Admin | AB25: -
A26: SCR-020 | B26: Platform Settings | C26: Super Admin / SaaS Administration | D26: Phase 3 | E26: US-0039, US-0040 | I26: Ready | J26: Not started | K26: Not started | L26: Not assessed | M26: Not assessed | N26: Not assessed | P26: Not scheduled | R26: No platform settings screen | U26: 46285 | W26: =IF(P26="Production",IF(X26="Yes","Released","Review release"),IF(P26="Rolled back","Rolled back",IF(OR(Q26<>"",COUNTIFS(J26:N26,"Blocked")>0),"Blocked",IF(OR(M26="Failed",N26="Rejected",AND(ISNUMBER(O26),O26>0)),"Rework",IF(X26="Yes","Ready for release",IF(N26="Accepted","Verify completion",IF(OR(M26="Passed",M26="In progress",N26="In review"),"Testing / review",IF(OR(COUNTIFS(J26:L26,"In progress")>0,COUNTIFS(J26:L26,"In review")>0,COUNTIFS(J26:L26,"Done")>0),"In progress",IF(COUNTIFS(J26:N26,"Not assessed")=5,"Not assessed","Planned"))))))))) | X26: =IF(AND(J26="Done",OR(K26="Done",K26="Not required"),OR(L26="Done",L26="Not required"),M26="Passed",N26="Accepted",ISNUMBER(O26),O26=0,Q26="",F26<>"",S26<>"",T26<>"",ISNUMBER(U26),OR(AND(K26<>"Not required",L26<>"Not required"),V26<>""),P26<>"Rolled back"),"Yes","No") | Y26: =IF(X26="Yes","Completed",IF(H26="","No deadline",IF(NOT(ISNUMBER(H26)),"Check date",IF(H26<Overview!$I$3,"Overdue",IF(H26<=Overview!$I$3+7,"Due soon","On track"))))) | Z26: =IF(AND(X26<>"Yes",ISNUMBER(H26)),MAX(0,Overview!$I$3-H26),0) | AA26: Super Admin | AB26: -
... A302: SCR-296 | B302: Notification Center | C302: Events / PTM / Communication | D302: MVP | E302: US-0591, US-0592 | I302: Ready | J302: In progress | K302: In progress | L302: Not assessed | M302: Not assessed | N302: Not assessed | P302: Not scheduled | R302: Parents only; staff have no inbox page | U302: 46285 | W302: =IF(P302="Production",IF(X302="Yes","Released","Review release"),IF(P302="Rolled back","Rolled back",IF(OR(Q302<>"",COUNTIFS(J302:N302,"Blocked")>0),"Blocked",IF(OR(M302="Failed",N302="Rejected",AND(ISNUMBER(O302),O302>0)),"Rework",IF(X302="Yes","Ready for release",IF(N302="Accepted","Verify completion",IF(OR(M302="Passed",M302="In progress",N302="In review"),"Testing / review",IF(OR(COUNTIFS(J302:L302,"In progress")>0,COUNTIFS(J302:L302,"In review")>0,COUNTIFS(J302:L302,"Done")>0),"In progress",IF(COUNTIFS(J302:N302,"Not assessed")=5,"Not assessed","Planned"))))))))) | X302: =IF(AND(J302="Done",OR(K302="Done",K302="Not required"),OR(L302="Done",L302="Not required"),M302="Passed",N302="Accepted",ISNUMBER(O302),O302=0,Q302="",F302<>"",S302<>"",T302<>"",ISNUMBER(U302),OR(AND(K302<>"Not required",L302<>"Not required"),V302<>""),P302<>"Rolled back"),"Yes","No") | Y302: =IF(X302="Yes","Completed",IF(H302="","No deadline",IF(NOT(ISNUMBER(H302)),"Check date",IF(H302<Overview!$I$3,"Overdue",IF(H302<=Overview!$I$3+7,"Due soon","On track"))))) | Z302: =IF(AND(X302<>"Yes",ISNUMBER(H302)),MAX(0,Overview!$I$3-H302),0) | AA302: All Users | AB302: /parent/notices

Sheet Shared Work
A2: Shared development work
A3: Proposed cross-screen backlog. Confirm applicability. These items are separate from the 296-screen count.
A4: Done requires an owner, evidence and no blocker. Use Not required only with a reason in the evidence field.
A6: Work ID | B6: Shared deliverable | C6: Owner | D6: Sprint | E6: Due date | F6: Status | G6: Blocker / dependency | H6: Evidence / reason | I6: Next action | J6: Verified | K6: Schedule
A7: SH-001 | B7: Development and staging environments | F7: Not assessed | J7: =IF(AND(F7="Done",C7<>"",H7<>"",G7=""),"Yes",IF(AND(F7="Not required",H7<>""),"Not required","No")) | K7: =IF(J7="Yes","Completed",IF(J7="Not required","Not required",IF(E7="","No deadline",IF(NOT(ISNUMBER(E7)),"Check date",IF(E7<Overview!$I$3,"Overdue",IF(E7<=Overview!$I$3+7,"Due soon","On track"))))))
A8: SH-002 | B8: Database schema and migrations | F8: Not assessed | J8: =IF(AND(F8="Done",C8<>"",H8<>"",G8=""),"Yes",IF(AND(F8="Not required",H8<>""),"Not required","No")) | K8: =IF(J8="Yes","Completed",IF(J8="Not required","Not required",IF(E8="","No deadline",IF(NOT(ISNUMBER(E8)),"Check date",IF(E8<Overview!$I$3,"Overdue",IF(E8<=Overview!$I$3+7,"Due soon","On track"))))))
A9: SH-003 | B9: Authentication and session management | F9: Not assessed | J9: =IF(AND(F9="Done",C9<>"",H9<>"",G9=""),"Yes",IF(AND(F9="Not required",H9<>""),"Not required","No")) | K9: =IF(J9="Yes","Completed",IF(J9="Not required","Not required",IF(E9="","No deadline",IF(NOT(ISNUMBER(E9)),"Check date",IF(E9<Overview!$I$3,"Overdue",IF(E9<=Overview!$I$3+7,"Due soon","On track"))))))
A10: SH-004 | B10: Role and permission enforcement | F10: Not assessed | J10: =IF(AND(F10="Done",C10<>"",H10<>"",G10=""),"Yes",IF(AND(F10="Not required",H10<>""),"Not required","No")) | K10: =IF(J10="Yes","Completed",IF(J10="Not required","Not required",IF(E10="","No deadline",IF(NOT(ISNUMBER(E10)),"Check date",IF(E10<Overview!$I$3,"Overdue",IF(E10<=Overview!$I$3+7,"Due soon","On track"))))))
A11: SH-005 | B11: School / tenant data isolation | F11: Not assessed | J11: =IF(AND(F11="Done",C11<>"",H11<>"",G11=""),"Yes",IF(AND(F11="Not required",H11<>""),"Not required","No")) | K11: =IF(J11="Yes","Completed",IF(J11="Not required","Not required",IF(E11="","No deadline",IF(NOT(ISNUMBER(E11)),"Check date",IF(E11<Overview!$I$3,"Overdue",IF(E11<=Overview!$I$3+7,"Due soon","On track"))))))
A12: SH-006 | B12: Shared UI components and routing | F12: Not assessed | J12: =IF(AND(F12="Done",C12<>"",H12<>"",G12=""),"Yes",IF(AND(F12="Not required",H12<>""),"Not required","No")) | K12: =IF(J12="Yes","Completed",IF(J12="Not required","Not required",IF(E12="","No deadline",IF(NOT(ISNUMBER(E12)),"Check date",IF(E12<Overview!$I$3,"Overdue",IF(E12<=Overview!$I$3+7,"Due soon","On track"))))))
A13: SH-007 | B13: File upload and document storage | F13: Not assessed | J13: =IF(AND(F13="Done",C13<>"",H13<>"",G13=""),"Yes",IF(AND(F13="Not required",H13<>""),"Not required","No")) | K13: =IF(J13="Yes","Completed",IF(J13="Not required","Not required",IF(E13="","No deadline",IF(NOT(ISNUMBER(E13)),"Check date",IF(E13<Overview!$I$3,"Overdue",IF(E13<=Overview!$I$3+7,"Due soon","On track"))))))
A14: SH-008 | B14: Notification delivery integration | F14: Not assessed | J14: =IF(AND(F14="Done",C14<>"",H14<>"",G14=""),"Yes",IF(AND(F14="Not required",H14<>""),"Not required","No")) | K14: =IF(J14="Yes","Completed",IF(J14="Not required","Not required",IF(E14="","No deadline",IF(NOT(ISNUMBER(E14)),"Check date",IF(E14<Overview!$I$3,"Overdue",IF(E14<=Overview!$I$3+7,"Due soon","On track"))))))
A15: SH-009 | B15: Payment provider integration | F15: Not assessed | J15: =IF(AND(F15="Done",C15<>"",H15<>"",G15=""),"Yes",IF(AND(F15="Not required",H15<>""),"Not required","No")) | K15: =IF(J15="Yes","Completed",IF(J15="Not required","Not required",IF(E15="","No deadline",IF(NOT(ISNUMBER(E15)),"Check date",IF(E15<Overview!$I$3,"Overdue",IF(E15<=Overview!$I$3+7,"Due soon","On track"))))))
A16: SH-010 | B16: Background jobs and scheduled work | F16: Not assessed | J16: =IF(AND(F16="Done",C16<>"",H16<>"",G16=""),"Yes",IF(AND(F16="Not required",H16<>""),"Not required","No")) | K16: =IF(J16="Yes","Completed",IF(J16="Not required","Not required",IF(E16="","No deadline",IF(NOT(ISNUMBER(E16)),"Check date",IF(E16<Overview!$I$3,"Overdue",IF(E16<=Overview!$I$3+7,"Due soon","On track"))))))
A17: SH-011 | B17: Report and export services | F17: Not assessed | J17: =IF(AND(F17="Done",C17<>"",H17<>"",G17=""),"Yes",IF(AND(F17="Not required",H17<>""),"Not required","No")) | K17: =IF(J17="Yes","Completed",IF(J17="Not required","Not required",IF(E17="","No deadline",IF(NOT(ISNUMBER(E17)),"Check date",IF(E17<Overview!$I$3,"Overdue",IF(E17<=Overview!$I$3+7,"Due soon","On track"))))))
A18: SH-012 | B18: Automated test framework | F18: Not assessed | J18: =IF(AND(F18="Done",C18<>"",H18<>"",G18=""),"Yes",IF(AND(F18="Not required",H18<>""),"Not required","No")) | K18: =IF(J18="Yes","Completed",IF(J18="Not required","Not required",IF(E18="","No deadline",IF(NOT(ISNUMBER(E18)),"Check date",IF(E18<Overview!$I$3,"Overdue",IF(E18<=Overview!$I$3+7,"Due soon","On track"))))))
... A22: SH-016 | B22: Deployment pipeline and release checks | F22: Not assessed | J22: =IF(AND(F22="Done",C22<>"",H22<>"",G22=""),"Yes",IF(AND(F22="Not required",H22<>""),"Not required","No")) | K22: =IF(J22="Yes","Completed",IF(J22="Not required","Not required",IF(E22="","No deadline",IF(NOT(ISNUMBER(E22)),"Check date",IF(E22<Overview!$I$3,"Overdue",IF(E22<=Overview!$I$3+7,"Due soon","On track"))))))
