Workbook

Sheet ERP Blueprint
A1: School Management ERP — Complete Screen Blueprint
A3: A complete UI/UX and development inventory covering 295 screens across 25 ERP modules.
A5: TOTAL SCREENS | D5: MODULES | G5: DELIVERY PHASES
A6: =COUNTA('Master Screens'!A2:A296) -> 295 | D6: 25 | G6: 3
A9: Priority | B9: Screen Count | C9: Purpose | D9: Recommended Release
A10: MVP | B10: =COUNTIF('Master Screens'!K$2:K$296,"MVP") -> 100 | C10: Core school operations needed for first production launch. | D10: Release 1
A11: Phase 2 | B11: =COUNTIF('Master Screens'!K$2:K$296,"Phase 2") -> 92 | C11: Operational expansion, automation and supporting departments. | D11: Release 2
A12: Phase 3 | B12: =COUNTIF('Master Screens'!K$2:K$296,"Phase 3") -> 103 | C12: Advanced / optional modules and deeper analytics. | D12: Release 3
A15: Module | B15: Screens | C15: MVP | D15: Phase 2 / 3
A16: Public Website & Authentication | B16: =COUNTIF('Master Screens'!B$2:B$296,A16) -> 8 | C16: =COUNTIFS('Master Screens'!B$2:B$296,A16,'Master Screens'!K$2:K$296,"MVP") -> 5 | D16: =B16-C16 -> 3
A17: Super Admin / SaaS Administration | B17: =COUNTIF('Master Screens'!B$2:B$296,A17) -> 12 | C17: =COUNTIFS('Master Screens'!B$2:B$296,A17,'Master Screens'!K$2:K$296,"MVP") -> 3 | D17: =B17-C17 -> 9
A18: Organization / School / Branch Setup | B18: =COUNTIF('Master Screens'!B$2:B$296,A18) -> 12 | C18: =COUNTIFS('Master Screens'!B$2:B$296,A18,'Master Screens'!K$2:K$296,"MVP") -> 8 | D18: =B18-C18 -> 4
A19: Role Dashboards | B19: =COUNTIF('Master Screens'!B$2:B$296,A19) -> 10 | C19: =COUNTIFS('Master Screens'!B$2:B$296,A19,'Master Screens'!K$2:K$296,"MVP") -> 5 | D19: =B19-C19 -> 5
A20: Admissions & Enquiries | B20: =COUNTIF('Master Screens'!B$2:B$296,A20) -> 12 | C20: =COUNTIFS('Master Screens'!B$2:B$296,A20,'Master Screens'!K$2:K$296,"MVP") -> 7 | D20: =B20-C20 -> 5
A21: Students | B21: =COUNTIF('Master Screens'!B$2:B$296,A21) -> 16 | C21: =COUNTIFS('Master Screens'!B$2:B$296,A21,'Master Screens'!K$2:K$296,"MVP") -> 8 | D21: =B21-C21 -> 8
A22: Parents & Guardians | B22: =COUNTIF('Master Screens'!B$2:B$296,A22) -> 9 | C22: =COUNTIFS('Master Screens'!B$2:B$296,A22,'Master Screens'!K$2:K$296,"MVP") -> 4 | D22: =B22-C22 -> 5
A23: Teachers & Staff | B23: =COUNTIF('Master Screens'!B$2:B$296,A23) -> 12 | C23: =COUNTIFS('Master Screens'!B$2:B$296,A23,'Master Screens'!K$2:K$296,"MVP") -> 6 | D23: =B23-C23 -> 6
A24: Academics & Curriculum | B24: =COUNTIF('Master Screens'!B$2:B$296,A24) -> 18 | C24: =COUNTIFS('Master Screens'!B$2:B$296,A24,'Master Screens'!K$2:K$296,"MVP") -> 9 | D24: =B24-C24 -> 9
A25: Student Attendance | B25: =COUNTIF('Master Screens'!B$2:B$296,A25) -> 10 | C25: =COUNTIFS('Master Screens'!B$2:B$296,A25,'Master Screens'!K$2:K$296,"MVP") -> 5 | D25: =B25-C25 -> 5
A26: Timetable & Substitution | B26: =COUNTIF('Master Screens'!B$2:B$296,A26) -> 8 | C26: =COUNTIFS('Master Screens'!B$2:B$296,A26,'Master Screens'!K$2:K$296,"MVP") -> 4 | D26: =B26-C26 -> 4
A27: Homework & Assignments | B27: =COUNTIF('Master Screens'!B$2:B$296,A27) -> 10 | C27: =COUNTIFS('Master Screens'!B$2:B$296,A27,'Master Screens'!K$2:K$296,"MVP") -> 6 | D27: =B27-C27 -> 4
... A40: Settings / Roles / Permissions / Audit | B40: =COUNTIF('Master Screens'!B$2:B$296,A40) -> 12 | C40: =COUNTIFS('Master Screens'!B$2:B$296,A40,'Master Screens'!K$2:K$296,"MVP") -> 5 | D40: =B40-C40 -> 7

Sheet Master Screens
A1: Screen ID | B1: Module | C1: Submodule | D1: Screen Name | E1: Primary Roles | F1: Portal | G1: Screen Type | H1: Purpose | I1: Key Actions | J1: Key Data / Fields | K1: Priority | L1: Reusable UI Pattern | M1: Implementation Notes
A2: SCR-001 | B2: Public Website & Authentication | C2: Public Website | D2: Landing / Home | E2: All Users | F2: Shared / Public | G2: Workflow / Management | H2: Manage the end-to-end landing / home workflow within public website & authentication. | I2: View, Create / Update, Filter, Export / Print | J2: Name / title, code, academic year, status, owner, dates, remarks | K2: MVP | L2: Workflow / Approval / Detail | M2: Preserve existing role permissions, APIs and workflows; design reusable responsive UI.
A3: SCR-002 | B3: Public Website & Authentication | C3: Public Website | D3: Workspace / Role Selection | E3: All Users | F3: Shared / Public | G3: Workflow / Management | H3: Manage the end-to-end workspace / role selection workflow within public website & authentication. | I3: View, Create / Update, Filter, Export / Print | J3: User, role, module, permission, scope, status, last login | K3: MVP | L3: Workflow / Approval / Detail | M3: Preserve existing role permissions, APIs and workflows; design reusable responsive UI.
A4: SCR-003 | B4: Public Website & Authentication | C4: Public Website | D4: Sign In | E4: All Users | F4: Shared / Public | G4: Workflow / Management | H4: Manage the end-to-end sign in workflow within public website & authentication. | I4: View, Create / Update, Filter, Export / Print | J4: Name / title, code, academic year, status, owner, dates, remarks | K4: MVP | L4: Workflow / Approval / Detail | M4: Preserve existing role permissions, APIs and workflows; design reusable responsive UI.
A5: SCR-004 | B5: Public Website & Authentication | C5: Public Website | D5: Forgot Password | E5: All Users | F5: Shared / Public | G5: Workflow / Management | H5: Manage the end-to-end forgot password workflow within public website & authentication. | I5: View, Create / Update, Filter, Export / Print | J5: Name / title, code, academic year, status, owner, dates, remarks | K5: MVP | L5: Workflow / Approval / Detail | M5: Preserve existing role permissions, APIs and workflows; design reusable responsive UI.
A6: SCR-005 | B6: Public Website & Authentication | C6: Public Website | D6: Reset Password | E6: All Users | F6: Shared / Public | G6: Workflow / Management | H6: Manage the end-to-end reset password workflow within public website & authentication. | I6: View, Create / Update, Filter, Export / Print | J6: Name / title, code, academic year, status, owner, dates, remarks | K6: MVP | L6: Workflow / Approval / Detail | M6: Preserve existing role permissions, APIs and workflows; design reusable responsive UI.
A7: SCR-006 | B7: Public Website & Authentication | C7: Public Website | D7: OTP / Two-Factor Verification | E7: All Users | F7: Shared / Public | G7: Workflow / Management | H7: Manage the end-to-end otp / two-factor verification workflow within public website & authentication. | I7: Review, Approve / Reject, Comment, Track status | J7: Name / title, code, academic year, status, owner, dates, remarks | K7: Phase 2 | L7: Workflow / Approval / Detail | M7: Preserve existing role permissions, APIs and workflows; design reusable responsive UI.
A8: SCR-007 | B8: Public Website & Authentication | C8: Public Website | D8: First Login / Change Password | E8: All Users | F8: Shared / Public | G8: Workflow / Management | H8: Manage the end-to-end first login / change password workflow within public website & authentication. | I8: View, Create / Update, Filter, Export / Print | J8: Name / title, code, academic year, status, owner, dates, remarks | K8: Phase 2 | L8: Workflow / Approval / Detail | M8: Preserve existing role permissions, APIs and workflows; design reusable responsive UI.
A9: SCR-008 | B9: Public Website & Authentication | C9: Public Website | D9: Access Denied / Session Expired | E9: All Users | F9: Shared / Public | G9: Workflow / Management | H9: Manage the end-to-end access denied / session expired workflow within public website & authentication. | I9: View, Create / Update, Filter, Export / Print | J9: Name / title, code, academic year, status, owner, dates, remarks | K9: Phase 2 | L9: Workflow / Approval / Detail | M9: Preserve existing role permissions, APIs and workflows; design reusable responsive UI.
A10: SCR-009 | B10: Super Admin / SaaS Administration | C10: Super Admin | D10: Platform Dashboard | E10: Super Admin | F10: Super Admin Portal | G10: Dashboard | H10: Provide an at-a-glance operational view of super admin / saas administration with key status, alerts and shortcuts. | I10: Filter, Drill down, Export, Print | J10: KPIs, alerts, recent activity, pending actions, date / academic-year filters | K10: MVP | L10: Dashboard + KPI Cards | M10: Preserve existing role permissions, APIs and workflows; design reusable responsive UI.
A11: SCR-010 | B11: Super Admin / SaaS Administration | C11: Super Admin | D11: Organizations List | E11: Super Admin | F11: Super Admin Portal | G11: List / Management | H11: Search, filter and manage records for organizations list. | I11: Search, Filter, Sort, Open record | J11: Name / title, code, academic year, status, owner, dates, remarks | K11: MVP | L11: Search + Filter + Data Table | M11: Preserve existing role permissions, APIs and workflows; design reusable responsive UI.
A12: SCR-011 | B12: Super Admin / SaaS Administration | C12: Super Admin | D12: Add Organization | E12: Super Admin | F12: Super Admin Portal | G12: Create / Transaction | H12: Capture or process the add organization workflow while enforcing school rules and validations. | I12: Create, Save, Validate, Cancel | J12: Name / title, code, academic year, status, owner, dates, remarks | K12: MVP | L12: Form / Wizard | M12: Preserve existing role permissions, APIs and workflows; design reusable responsive UI.
... A296: SCR-295 | B296: Settings / Roles / Permissions / Audit | C296: Security & Configuration | D296: Data Import / Export / Backup | E296: IT Admin, School Admin, Super Admin | F296: School Admin / Shared | G296: Workflow / Management | H296: Manage the end-to-end data import / export / backup workflow within settings / roles / permissions / audit. | I296: Upload, Validate, Preview, Confirm | J296: Name / title, code, academic year, status, owner, dates, remarks | K296: Phase 3 | L296: Workflow / Approval / Detail | M296: Preserve existing role permissions, APIs and workflows; design reusable responsive UI.

Sheet Role Coverage
A1: Role Coverage & Portal Planning
A4: Role | B4: Accessible / Relevant Screens* | C4: Primary Portal | D4: Typical Focus | E4: UI Emphasis
A5: Super Admin | B5: =COUNTIF('Master Screens'!E$2:E$296,"*Super Admin*") -> 36 | C5: Super Admin Portal | D5: Tenant, plans, platform users, service health | E5: Dense dashboards, filters, approvals, drill-down
A6: Organization Admin | B6: =COUNTIF('Master Screens'!E$2:E$296,"*Organization Admin*") -> 12 | C6: School Admin / Staff Portal | D6: Schools, branches, group-level setup | E6: Dense dashboards, filters, approvals, drill-down
A7: School Admin | B7: =COUNTIF('Master Screens'!E$2:E$296,"*School Admin*") -> 257 | C7: School Admin / Staff Portal | D7: Whole-school operations, approvals, configuration | E7: Dense dashboards, filters, approvals, drill-down
A8: Principal | B8: =COUNTIF('Master Screens'!E$2:E$296,"*Principal*") -> 141 | C8: School Admin / Staff Portal | D8: Academic, attendance, approvals, performance | E8: Dense dashboards, filters, approvals, drill-down
A9: Academic Coordinator | B9: =COUNTIF('Master Screens'!E$2:E$296,"*Academic Coordinator*") -> 26 | C9: School Admin / Staff Portal | D9: Curriculum, timetable, lesson plans, syllabus | E9: Fast actions, readable tables, minimal clicks
A10: Admission Officer | B10: =COUNTIF('Master Screens'!E$2:E$296,"*Admission Officer*") -> 20 | C10: School Admin / Staff Portal | D10: Enquiries, applications, verification, admission | E10: Task-focused, compact, operational
A11: Receptionist | B11: =COUNTIF('Master Screens'!E$2:E$296,"*Receptionist*") -> 20 | C11: School Admin / Staff Portal | D11: Enquiries, visitors, appointments, gate workflows | E11: Task-focused, compact, operational
A12: Teacher | B12: =COUNTIF('Master Screens'!E$2:E$296,"*Teacher*") -> 118 | C12: Teacher Portal | D12: Classes, attendance, homework, marks, communication | E12: Fast actions, readable tables, minimal clicks
A13: Class Teacher | B13: =COUNTIF('Master Screens'!E$2:E$296,"*Class Teacher*") -> 35 | C13: Teacher Portal | D13: Class attendance, students, parents, progress | E13: Fast actions, readable tables, minimal clicks
A14: Student | B14: =COUNTIF('Master Screens'!E$2:E$296,"*Student*") -> 55 | C14: Student Portal | D14: Learning, timetable, homework, exams, attendance | E14: Bright, simple, mobile-friendly, clear status
A15: Parent | B15: =COUNTIF('Master Screens'!E$2:E$296,"*Parent*") -> 66 | C15: Parent Portal | D15: Child progress, attendance, fees, messages, transport | E15: Bright, simple, mobile-friendly, clear status
A16: Accountant | B16: =COUNTIF('Master Screens'!E$2:E$296,"*Accountant*") -> 31 | C16: School Admin / Staff Portal | D16: Fees, receipts, ledgers, finance | E16: Task-focused, compact, operational
A17: HR | B17: =COUNTIF('Master Screens'!E$2:E$296,"*HR*") -> 33 | C17: School Admin / Staff Portal | D17: Staff, attendance, leave, recruitment, payroll | E17: Task-focused, compact, operational
A18: Employee | B18: =COUNTIF('Master Screens'!E$2:E$296,"*Employee*") -> 15 | C18: School Admin / Staff Portal | D18: Self-service attendance, leave, payslips | E18: Task-focused, compact, operational
A19: Exam Coordinator | B19: =COUNTIF('Master Screens'!E$2:E$296,"*Exam Coordinator*") -> 14 | C19: School Admin / Staff Portal | D19: Exam setup, schedule, marks, results | E19: Task-focused, compact, operational
A20: Transport Manager | B20: =COUNTIF('Master Screens'!E$2:E$296,"*Transport Manager*") -> 13 | C20: Operations Portal | D20: Routes, vehicles, students, trips, GPS | E20: Task-focused, compact, operational
A21: Driver / Conductor | B21: =COUNTIF('Master Screens'!E$2:E$296,"*Driver / Conductor*") -> 2 | C21: Operations Portal | D21: Trips, boarding/drop, route execution | E21: Task-focused, compact, operational
A22: Librarian | B22: =COUNTIF('Master Screens'!E$2:E$296,"*Librarian*") -> 11 | C22: Operations Portal | D22: Catalogue, issue/return, fines, reports | E22: Task-focused, compact, operational
A23: Hostel Warden | B23: =COUNTIF('Master Screens'!E$2:E$296,"*Hostel Warden*") -> 8 | C23: Operations Portal | D23: Rooms, attendance, leave, complaints | E23: Task-focused, compact, operational
A24: Nurse / Medical Officer | B24: =COUNTIF('Master Screens'!E$2:E$296,"*Nurse / Medical Officer*") -> 10 | C24: Operations Portal | D24: Medical profile, clinic visits, first aid | E24: Task-focused, compact, operational
A25: Counsellor | B25: =COUNTIF('Master Screens'!E$2:E$296,"*Counsellor*") -> 10 | C25: Operations Portal | D25: Appointments, confidential case follow-up | E25: Task-focused, compact, operational
A26: Security | B26: =COUNTIF('Master Screens'!E$2:E$296,"*Security*") -> 8 | C26: Operations Portal | D26: Visitors, passes, gate logs, incidents | E26: Task-focused, compact, operational
A27: Store Manager | B27: =COUNTIF('Master Screens'!E$2:E$296,"*Store Manager*") -> 12 | C27: Operations Portal | D27: Inventory, stock, suppliers, assets | E27: Task-focused, compact, operational
A28: Lab Assistant | B28: =COUNTIF('Master Screens'!E$2:E$296,"*Lab Assistant*") -> 12 | C28: Operations Portal | D28: Lab stock, equipment, bookings | E28: Task-focused, compact, operational
A29: IT Admin | B29: =COUNTIF('Master Screens'!E$2:E$296,"*IT Admin*") -> 12 | C29: School Admin / Staff Portal | D29: Users, roles, security, integrations, audit | E29: Task-focused, compact, operational
A31: *Counts are based on the Primary Roles column and are for planning access/navigation, not a replacement for the final RBAC permission matrix.

Sheet Delivery Plan
A1: Recommended Delivery Plan
A4: Phase | B4: Screen Count | C4: Goal | D4: Suggested Order | E4: Entry Criteria | F4: Exit Criteria | G4: Primary Users | H4: Design / Engineering Focus
A5: MVP | B5: =COUNTIF('Master Screens'!K$2:K$296,"MVP") -> 100 | C5: Run the core school lifecycle from setup and admission through academics, attendance, exams, fees and essential communication. | D5: Foundation → Auth → School Setup → Students/Staff → Admissions → Academics → Attendance → Homework → Exams → Fees → Core Reports | E5: Approved product scope, roles, academic structure and core data model. | F5: Core journeys pass UAT; role access works; responsive UI; no critical workflow gaps. | G5: School Admin, Principal, Teacher, Student, Parent, Admission, Accountant | H5: Reusable shell, sidebar, dashboard patterns, tables, forms, profiles, approvals.
A6: Phase 2 | B6: =COUNTIF('Master Screens'!K$2:K$296,"Phase 2") -> 92 | C6: Expand operations into HR, transport, library, security, inventory and advanced workflow automation. | D6: HR → Transport → Library → Security → Inventory → Advanced Communication → Extended Reports | E6: Stable MVP, production feedback, integrations clarified. | F6: Department workflows complete; reporting and integrations validated. | G6: HR, Transport, Librarian, Security, Store/Lab teams plus existing users | H6: Operational speed, bulk actions, device/GPS/payment integration readiness.
A7: Phase 3 | B7: =COUNTIF('Master Screens'!K$2:K$296,"Phase 3") -> 103 | C7: Add hostel, health/counselling, advanced analytics and other enterprise enhancements. | D7: Hostel → Health/Counselling → Advanced Reports → Custom Reporting / Optimization | E7: Phase 2 adoption, privacy/access requirements finalized. | F7: Optional enterprise modules accepted with strict access controls and auditability. | G7: Hostel Warden, Nurse, Counsellor, Leadership | H7: Sensitive-data UX, analytics depth, exception workflows, enterprise controls.
A10: Reusable UI Pattern | B10: Used For | C10: Core Components | D10: Design Direction
A11: Dashboard + KPI Cards | B11: Role dashboards and module dashboards | C11: KPI cards, alerts, charts, quick actions, recent activity | D11: Bright but controlled accents; no excessive card clutter
A12: Search + Filter + Data Table | B12: Directories, lists, masters | C12: Search, dropdown filters, table, status, action menu, pagination | D12: Compact, readable, sticky header where useful
A13: Profile / Detail + Tabs | B13: Student, staff, parent, asset, vehicle records | C13: Profile header, summary, tabs, timeline, actions | D13: Strong hierarchy; avoid card-inside-card layouts
A14: Form / Wizard | B14: Admissions, student/staff create, setup | C14: Grouped fields, dropdowns, validations, stepper when needed | D14: 44–48px controls; clear sections; minimal wasted space
A15: Calendar / Schedule | B15: Timetable, events, exams, interviews, PTM | C15: Calendar, day/week view, filters, assignment drawer | D15: Clear time hierarchy and conflict states
A16: Workflow / Approval / Detail | B16: Admissions, leave, verification, approvals | C16: Status stepper, detail, comments, approve/reject actions | D16: Prominent current status and audit trail
A17: Filters + KPI + Table / Chart | B17: Reports & analytics | C17: Filter bar, KPI summary, chart, table, export | D17: Data-first, printable, avoid decorative charts
A18: Settings / Master Data | B18: Configuration, roles, policies | C18: Tabs, compact forms, toggles, lists | D18: Stable, predictable, permission-aware
